Metadata-Version: 2.4
Name: burst-waveform
Version: 0.4.1
Summary: A Python package for gravitational wave burst waveform
Home-page: https://git.ligo.org/yumeng.xu/setup.py
Author: Yumeng Xu
Author-email: The PycWB team <yumeng.xu@ligo.org>
Keywords: ligo,sine-gaussian,white noise burst,gravitational waves,burst,waveform model
Requires-Python: >=3.8
License-File: LICENSE
Requires-Dist: numpy
Requires-Dist: gwpy
Dynamic: author
Dynamic: description
Dynamic: description-content-type
Dynamic: home-page
Dynamic: license-file
Dynamic: requires-dist
Dynamic: requires-python
